README.rst
setup.cfg
setup.py
freelancersdk/__init__.py
freelancersdk/exceptions.py
freelancersdk/session.py
freelancersdk.egg-info/PKG-INFO
freelancersdk.egg-info/SOURCES.txt
freelancersdk.egg-info/dependency_links.txt
freelancersdk.egg-info/requires.txt
freelancersdk.egg-info/top_level.txt
freelancersdk/resources/__init__.py
freelancersdk/resources/contests/__init__.py
freelancersdk/resources/contests/contests.py
freelancersdk/resources/contests/exceptions.py
freelancersdk/resources/contests/helpers.py
freelancersdk/resources/contests/types.py
freelancersdk/resources/messages/__init__.py
freelancersdk/resources/messages/exceptions.py
freelancersdk/resources/messages/helpers.py
freelancersdk/resources/messages/messages.py
freelancersdk/resources/messages/types.py
freelancersdk/resources/projects/__init__.py
freelancersdk/resources/projects/exceptions.py
freelancersdk/resources/projects/helpers.py
freelancersdk/resources/projects/projects.py
freelancersdk/resources/projects/types.py
freelancersdk/resources/users/__init__.py
freelancersdk/resources/users/exceptions.py
freelancersdk/resources/users/helpers.py
freelancersdk/resources/users/users.py