Metadata-Version: 1.1
Name: freelancersdk
Version: 0.1.5
Summary: Offical Freelancer.com SDK
Home-page: https://github.com/freelancer/freelancer-sdk-python
Author: Freelancer.com
Author-email: api-support@freelancer.com
License: UNKNOWN
Platform: UNKNOWN
Classifier: Development Status :: 4 - Beta
Classifier: Topic :: Software Development
Classifier: License :: OSI Approved :: GNU Lesser General Public License v3 (LGPLv3)
Classifier: Operating System :: OS Independent
Classifier: Programming Language :: Python :: 2.7
Classifier: Programming Language :: Python :: 3
Classifier: Programming Language :: Python :: 3.6
Classifier: Programming Language :: Python :: Implementation :: CPython
